{
  "BillingCurrency": "USD",
  "CustomerEntityId": "Default",
  "CustomerEntityType": "Retail",
  "Items": [
    {
      "currencyCode": "USD",
      "tierMinimumUnits": 0.0,
      "retailPrice": 0.0208,
      "unitPrice": 0.0208,
      "armRegionName": "eastus",
      "location": "US East",
      "effectiveStartDate": "2023-01-01T00:00:00Z",
      "meterId": "storage-lrs-meter-id",
      "meterName": "LRS Data Stored",
      "productId": "DZH317F1HKN0",
      "skuId": "DZH317F1HKN0/001S",
      "productName": "Storage",
      "skuName": "Standard LRS",
      "serviceName": "Storage",
      "serviceId": "DZH317F1HKN0",
      "serviceFamily": "Storage",
      "unitOfMeasure": "1 GB/Month",
      "type": "Consumption",
      "isPrimaryMeterRegion": true,
      "armSkuName": "Standard_LRS"
    },
    {
      "currencyCode": "USD",
      "tierMinimumUnits": 0.0,
      "retailPrice": 0.0208,
      "unitPrice": 0.0208,
      "armRegionName": "eastus",
      "location": "US East",
      "effectiveStartDate": "2023-01-01T00:00:00Z",
      "meterId": "storage-tables-meter-id",
      "meterName": "Tables",
      "productId": "DZH317F1HKN0",
      "skuId": "DZH317F1HKN0/002T",
      "productName": "Tables",
      "skuName": "Standard LRS",
      "serviceName": "Storage",
      "serviceId": "DZH317F1HKN0",
      "serviceFamily": "Storage",
      "unitOfMeasure": "1 GB/Month",
      "type": "Consumption",
      "isPrimaryMeterRegion": true,
      "armSkuName": "Standard_LRS"
    },
    {
      "currencyCode": "USD",
      "tierMinimumUnits": 0.0,
      "retailPrice": 0.0208,
      "unitPrice": 0.0208,
      "armRegionName": "eastus",
      "location": "US East",
      "effectiveStartDate": "2023-01-01T00:00:00Z",
      "meterId": "storage-queues-meter-id",
      "meterName": "Queues v2",
      "productId": "DZH317F1HKN0",
      "skuId": "DZH317F1HKN0/003Q",
      "productName": "Queues v2",
      "skuName": "Standard LRS",
      "serviceName": "Storage",
      "serviceId": "DZH317F1HKN0",
      "serviceFamily": "Storage",
      "unitOfMeasure": "1 GB/Month",
      "type": "Consumption",
      "isPrimaryMeterRegion": true,
      "armSkuName": "Standard_LRS"
    },
    {
      "currencyCode": "USD",
      "tierMinimumUnits": 0.0,
      "retailPrice": 0.0208,
      "unitPrice": 0.0208,
      "armRegionName": "eastus",
      "location": "US East",
      "effectiveStartDate": "2023-01-01T00:00:00Z",
      "meterId": "storage-blob-meter-id",
      "meterName": "General Block Blob",
      "productId": "DZH317F1HKN0",
      "skuId": "DZH317F1HKN0/004B",
      "productName": "General Block Blob",
      "skuName": "Standard LRS",
      "serviceName": "Storage",
      "serviceId": "DZH317F1HKN0",
      "serviceFamily": "Storage",
      "unitOfMeasure": "1 GB/Month",
      "type": "Consumption",
      "isPrimaryMeterRegion": true,
      "armSkuName": "Standard_LRS"
    },
    {
      "currencyCode": "USD",
      "tierMinimumUnits": 0.0,
      "retailPrice": 13.14,
      "unitPrice": 13.14,
      "armRegionName": "eastus",
      "location": "US East",
      "effectiveStartDate": "2023-01-01T00:00:00Z",
      "meterId": "app-service-b1-meter-id",
      "meterName": "B1 App Service Plan",
      "productId": "DZH317GT8G5N",
      "skuId": "DZH317GT8G5N/001B",
      "productName": "Azure App Service Basic Plan",
      "skuName": "B1",
      "serviceName": "App Service",
      "serviceId": "DZH317GT8G5N",
      "serviceFamily": "Compute",
      "unitOfMeasure": "1 Hour",
      "type": "Consumption",
      "isPrimaryMeterRegion": true,
      "armSkuName": "B1"
    },
    {
      "currencyCode": "USD",
      "tierMinimumUnits": 0.0,
      "retailPrice": 0.0,
      "unitPrice": 0.0,
      "armRegionName": "eastus",
      "location": "US East",
      "effectiveStartDate": "2023-01-01T00:00:00Z",
      "meterId": "web-app-meter-id",
      "meterName": "Web App",
      "productId": "DZH317GT8G5N",
      "skuId": "DZH317GT8G5N/002W",
      "productName": "Azure App Service Basic Plan",
      "skuName": "B1",
      "serviceName": "App Service",
      "serviceId": "DZH317GT8G5N",
      "serviceFamily": "Compute",
      "unitOfMeasure": "1 Hour",
      "type": "Consumption",
      "isPrimaryMeterRegion": true,
      "armSkuName": "B1"
    }
  ],
  "NextPageLink": null,
  "Count": 6
} 